metarace_trackmeet-1.13.6.dist-info/licenses/LICENSE
trackmeet/__init__.py
trackmeet/__main__.py
trackmeet/aggregate.py
trackmeet/classification.py
trackmeet/databridge.py
trackmeet/eventdb.py
trackmeet/f200.py
trackmeet/gemini.py
trackmeet/ittt.py
trackmeet/lapscore.py
trackmeet/ps.py
trackmeet/race.py
trackmeet/scbwin.py
trackmeet/sender.py
trackmeet/sprnd.py
trackmeet/uiutil.py
trackmeet/ui/classification.ui
trackmeet/ui/classification_properties.ui
trackmeet/ui/ittt.ui
trackmeet/ui/ittt_properties.ui
trackmeet/ui/ps.ui
trackmeet/ui/ps_properties.ui
trackmeet/ui/race.ui
trackmeet/ui/race_properties.ui
trackmeet/ui/sprnd.ui
trackmeet/ui/trackmeet.ui
metarace_trackmeet-1.13.6.dist-info/METADATA
metarace_trackmeet-1.13.6.dist-info/WHEEL
metarace_trackmeet-1.13.6.dist-info/entry_points.txt
metarace_trackmeet-1.13.6.dist-info/top_level.txt
metarace_trackmeet-1.13.6.dist-info/RECORD
