Metadata-Version: 2.4
Name: metarace-trackmeet
Version: 1.13.6
Summary: Timing and result application for track cycling events
Author-email: Nathan Fraser <ndf-zz@6-v.org>
License-Expression: MIT
Project-URL: homepage, https://github.com/ndf-zz/metarace-trackmeet
Keywords: velodrome,cycling,results,timing
Classifier: Development Status :: 3 - Alpha
Classifier: Topic :: Other/Nonlisted Topic
Classifier: Operating System :: OS Independent
Classifier: Programming Language :: Python :: 3
Requires-Python: >=3.11
License-File: LICENSE
Requires-Dist: metarace<2.2,>=2.1.21a1
Dynamic: license-file
